nnaps/__init__.py
nnaps/defaults.py
nnaps/differential_plot.py
nnaps/fileio.py
nnaps/predictors.py
nnaps/version.py
nnaps/mesa/__init__.py
nnaps/mesa/common_envelope.py
nnaps/mesa/compress_mesa.py
nnaps/mesa/defaults.py
nnaps/mesa/evolution_errors.py
nnaps/mesa/evolution_phases.py
nnaps/mesa/extract_mesa.py
nnaps/mesa/fileio.py
nnaps/mesa/helium_burn.data
nnaps/mesa/main.py
nnaps/reporting/__init__.py
nnaps/reporting/bokeh_ext.py
nnaps/reporting/html_reports.py
nnaps/reporting/pdf_reports.py
nnaps/tests/__init__.py
nnaps/tests/conftest.py
nnaps/tests/test_defaults.py
nnaps/tests/test_fileio.py
nnaps/tests/test_integration.py
nnaps/tests/test_mesa.py
nnaps/tests/test_mesa_ce.py
nnaps/tests/test_mesa_compress.py
nnaps/tests/test_mesa_evolution_errors.py
nnaps/tests/test_mesa_evolution_phases.py
nnaps/tests/test_mesa_extract.py
nnaps/tests/test_predictors_Base.py
nnaps/tests/test_predictors_FC.py
nnaps/tests/test_predictors_GB.py
nnaps-0.2.1.dist-info/LICENSE
nnaps-0.2.1.dist-info/METADATA
nnaps-0.2.1.dist-info/WHEEL
nnaps-0.2.1.dist-info/entry_points.txt
nnaps-0.2.1.dist-info/top_level.txt
nnaps-0.2.1.dist-info/RECORD
