Metadata-Version: 2.1
Name: nnaps
Version: 0.2.1
Summary: Neural Network assisted Population Synthesis tools
Home-page: https://github.com/vosjo/nnaps
Author: Joris Vos
Author-email: joris.vos@uv.cl
License: UNKNOWN
Platform: UNKNOWN
Classifier: Development Status :: 4 - Beta
Classifier: Programming Language :: Python :: 3
Classifier: License :: OSI Approved :: MIT License
Classifier: Operating System :: OS Independent
Classifier: Topic :: Scientific/Engineering :: Astronomy
Requires-Python: >=3.7
Requires-Dist: numpy (>=1.19)
Requires-Dist: scipy (>=1.3)
Requires-Dist: pandas (>=0.25)
Requires-Dist: keras (>=2.3)
Requires-Dist: scikit-learn (>=0.22.1)
Requires-Dist: pyyaml (>=5.3)
Requires-Dist: h5py (>=2.9)
Requires-Dist: matplotlib
Requires-Dist: bokeh
Requires-Dist: tables
Requires-Dist: six
Requires-Dist: astropy
